napari_micromanager/__init__.py
napari_micromanager/__main__.py
napari_micromanager/_core_link.py
napari_micromanager/_mda_handler.py
napari_micromanager/_util.py
napari_micromanager/main_window.py
napari_micromanager/napari.yaml
napari_micromanager/_gui_objects/__init__.py
napari_micromanager/_gui_objects/_illumination_widget.py
napari_micromanager/_gui_objects/_mda_widget.py
napari_micromanager/_gui_objects/_min_max_widget.py
napari_micromanager/_gui_objects/_shutters_widget.py
napari_micromanager/_gui_objects/_snap_live_widget.py
napari_micromanager/_gui_objects/_stages_widget.py
napari_micromanager/_gui_objects/_toolbar.py
napari_micromanager-0.1.0.dist-info/METADATA
napari_micromanager-0.1.0.dist-info/WHEEL
napari_micromanager-0.1.0.dist-info/entry_points.txt
napari_micromanager-0.1.0.dist-info/licenses/LICENSE
napari_micromanager-0.1.0.dist-info/RECORD
