Metadata-Version: 2.1
Name: napari-micromanager
Version: 0.1.0
Summary: Micro-Manager GUI interface in napari.
Project-URL: Source, https://github.com/pymmcore-plus/napari-micromanager
Project-URL: Tracker, https://github.com/pymmcore-plus/napari-micromanager/issues
Author-email: Federico Gasparoli <federico.gasparoli@gmail.com>, Talley Lambert <talley.lambert@gmail.com>
License: BSD 3-Clause License
License-File: LICENSE
Keywords: micro-manager,microscope,multi-processing,remote
Classifier: Development Status :: 3 - Alpha
Classifier: Framework :: napari
Classifier: Intended Audience :: Developers
Classifier: Intended Audience :: Science/Research
Classifier: License :: OSI Approved :: BSD License
Classifier: Operating System :: OS Independent
Classifier: Programming Language :: Python
Classifier: Programming Language :: Python :: 3
Classifier: Programming Language :: Python :: 3.8
Classifier: Programming Language :: Python :: 3.9
Classifier: Programming Language :: Python :: 3.10
Classifier: Programming Language :: Python :: 3.11
Classifier: Topic :: System :: Hardware
Classifier: Topic :: System :: Hardware :: Hardware Drivers
Classifier: Topic :: Utilities
Requires-Python: >=3.8
Requires-Dist: fonticon-materialdesignicons6
Requires-Dist: napari>=0.4.13
Requires-Dist: pymmcore-plus>=0.9.3
Requires-Dist: pymmcore-widgets>=0.7.0rc1
Requires-Dist: superqt>=0.5.1
Requires-Dist: tifffile
Requires-Dist: useq-schema>=0.4.1
Requires-Dist: zarr
Provides-Extra: dev
Requires-Dist: isort; extra == 'dev'
Requires-Dist: mda-simulator; extra == 'dev'
Requires-Dist: mypy; extra == 'dev'
Requires-Dist: pre-commit; extra == 'dev'
Requires-Dist: ruff; extra == 'dev'
Provides-Extra: pyqt5
Requires-Dist: pyqt5; extra == 'pyqt5'
Provides-Extra: pyqt6
Requires-Dist: pyqt6; extra == 'pyqt6'
Provides-Extra: pyside2
Requires-Dist: pyside2; extra == 'pyside2'
Provides-Extra: pyside6
Requires-Dist: pyside6; extra == 'pyside6'
Provides-Extra: test
Requires-Dist: pytest; extra == 'test'
Requires-Dist: pytest-cov; extra == 'test'
Requires-Dist: pytest-qt; extra == 'test'
